duyo/__init__.py
duyo/license.py
duyo-0.0.1b2.dist-info/METADATA
duyo-0.0.1b2.dist-info/WHEEL
duyo-0.0.1b2.dist-info/top_level.txt
duyo-0.0.1b2.dist-info/RECORD
