Metadata-Version: 2.1
Name: duyo
Version: 0.0.1b2
Summary: duyo modules
Home-page: https://github.com/westsea314/duyo
Author: westsea314
Author-email: westsea314@gmail.com
Keywords: duyo,duyo module,duyo-kr
